mainpack/__init__.py
mathoprations-0.2.dist-info/LICENCE.txt
mathoprations-0.2.dist-info/METADATA
mathoprations-0.2.dist-info/WHEEL
mathoprations-0.2.dist-info/top_level.txt
mathoprations-0.2.dist-info/RECORD
