Metadata-Version: 2.1
Name: mathoprations
Version: 0.2
Summary: <Basic desc>
Home-page: UNKNOWN
Author: sachin
Author-email: hsgh@gmail.com
License: UNKNOWN
Platform: UNKNOWN
Classifier: Programming Language :: Python :: 3
Classifier: License :: OSI Approved :: MIT License
Classifier: Operating System :: OS Independent
License-File: LICENCE.txt
